app_simulator/__init__.py
app_simulator/__main__.py
app_simulator/app_config.py
app_simulator/fields.py
app_simulator/form.py
app_simulator/routes.py
app_simulator/rss.py
app_simulator/samples.py
app_simulator/storage.py
app_simulator/utils.py
app_simulator/static/js/datasource.js
app_simulator/static/js/widget_form.js
app_simulator/static/shim/Intl.min.js
app_simulator/static/shim/signage.js
app_simulator/templates/base.html
app_simulator/templates/list_files.html
app_simulator/templates/widget_exceptions.html
app_simulator/templates/widget_form.html
onsigntv_app_simulator-1.5.0.data/data/requirements-dev.txt
onsigntv_app_simulator-1.5.0.data/data/requirements.txt
onsigntv_app_simulator-1.5.0.dist-info/LICENSE
onsigntv_app_simulator-1.5.0.dist-info/METADATA
onsigntv_app_simulator-1.5.0.dist-info/WHEEL
onsigntv_app_simulator-1.5.0.dist-info/entry_points.txt
onsigntv_app_simulator-1.5.0.dist-info/top_level.txt
onsigntv_app_simulator-1.5.0.dist-info/RECORD
