Metadata-Version: 2.1
Name: onsigntv-app-simulator
Version: 1.5.0
Summary: Assist the development of apps for OnSign TV platform by running them locally.
Home-page: https://github.com/onsigntv/app-simulator
Author: OnSign TV
Author-email: support@onsign.tv
License: MIT
Project-URL: Bug Tracker, https://github.com/onsigntv/app-simulator/issues
Keywords: development onsigntv apps
Platform: UNKNOWN
Classifier: Development Status :: 4 - Beta
Classifier: Environment :: Console
Classifier: Intended Audience :: Developers
Classifier: License :: OSI Approved :: MIT License
Classifier: Natural Language :: English
Classifier: Operating System :: MacOS :: MacOS X
Classifier: Operating System :: POSIX :: Linux
Classifier: Programming Language :: Python :: 3
Classifier: Programming Language :: Python :: 3.8
Classifier: Programming Language :: Python :: 3.9
Classifier: Programming Language :: Python :: 3.10
Classifier: Programming Language :: Python :: 3.11
Classifier: Programming Language :: Python :: 3.12
Classifier: Topic :: Software Development
Requires-Python: >=3.8
Requires-Dist: aiohttp-sse (==2.2.0)
Requires-Dist: aiohttp (==3.9.5)
Requires-Dist: feedparser (==6.0.10)
Requires-Dist: Jinja2 (==2.11.3)
Requires-Dist: lorem (==0.1.1)
Requires-Dist: Pillow (==10.4.0)
Requires-Dist: pytz (==2022.1)
Requires-Dist: qrcode (==7.3.1)
Requires-Dist: WTForms (==2.3.3)
Requires-Dist: MarkupSafe (==1.1.1)
Provides-Extra: dev
Requires-Dist: pre-commit (==3.3.2) ; extra == 'dev'
Requires-Dist: ruff (==0.3.0) ; extra == 'dev'
